appsync_gremlin/AppSync.py
appsync_gremlin/__init__.py
appsync_gremlin/filter/Filter.py
appsync_gremlin/filter/__init__.py
appsync_gremlin/helpers/Exceptions.py
appsync_gremlin/helpers/__init__.py
appsync_gremlin/resolver/Resolver.py
appsync_gremlin/resolver/ResolverInput.py
appsync_gremlin/resolver/__init__.py
appsync_gremlin-0.0.19.dist-info/METADATA
appsync_gremlin-0.0.19.dist-info/WHEEL
appsync_gremlin-0.0.19.dist-info/top_level.txt
appsync_gremlin-0.0.19.dist-info/RECORD
