Metadata-Version: 2.1
Name: appsync-gremlin
Version: 0.0.19
Summary: A simple Python interface for AppSync resolvers and Gremlin traversals.
Home-page: UNKNOWN
Author: Alistair O'Brien
Author-email: alistair@duneroot.co.uk
License: UNKNOWN
Platform: UNKNOWN
Requires-Dist: gremlinpython
